sunds/__init__.py
sunds/conftest.py
sunds/typing.py
sunds/core/__init__.py
sunds/core/dataset_builder.py
sunds/core/dataset_semantic_types.py
sunds/core/load_utils.py
sunds/core/load_utils_test.py
sunds/core/spec_dict.py
sunds/core/spec_dict_test.py
sunds/core/specs.py
sunds/core/specs_base.py
sunds/core/specs_utils.py
sunds/core/tasks.py
sunds/core/np_geometry/__init__.py
sunds/core/np_geometry/isometry.py
sunds/core/np_geometry/isometry_test.py
sunds/core/tf_geometry/__init__.py
sunds/core/tf_geometry/cameras.py
sunds/core/tf_geometry/cameras_test.py
sunds/core/tf_geometry/isometry.py
sunds/core/tf_geometry/isometry_test.py
sunds/core/tf_geometry/rays.py
sunds/core/tf_geometry/rays_test.py
sunds/datasets/__init__.py
sunds/datasets/nerf_synthetic/builder_utils.py
sunds/datasets/nerf_synthetic/checksums.tsv
sunds/datasets/nerf_synthetic/frames_builder.py
sunds/datasets/nerf_synthetic/frames_builder_test.py
sunds/datasets/nerf_synthetic/scenes_builder.py
sunds/datasets/nerf_synthetic/scenes_builder_test.py
sunds/datasets/nerf_synthetic/dummy_data/nerf_synthetic/lego/transforms_test.json
sunds/datasets/nerf_synthetic/dummy_data/nerf_synthetic/lego/transforms_train.json
sunds/datasets/nerf_synthetic/dummy_data/nerf_synthetic/lego/transforms_val.json
sunds/datasets/nerf_synthetic/dummy_data/nerf_synthetic/lego/test/r_0.png
sunds/datasets/nerf_synthetic/dummy_data/nerf_synthetic/lego/test/r_1.png
sunds/datasets/nerf_synthetic/dummy_data/nerf_synthetic/lego/train/r_0.png
sunds/datasets/nerf_synthetic/dummy_data/nerf_synthetic/lego/train/r_1.png
sunds/datasets/nerf_synthetic/dummy_data/nerf_synthetic/lego/val/r_0.png
sunds/datasets/nerf_synthetic/dummy_data/nerf_synthetic/lego/val/r_1.png
sunds/features/__init__.py
sunds/features/normal.py
sunds/features/normal_test.py
sunds/tasks/__init__.py
sunds/tasks/boundaries_utils.py
sunds/tasks/boundaries_utils_test.py
sunds/tasks/default_tasks.py
sunds/tasks/default_tasks_test.py
sunds/tasks/nerf.py
sunds/tasks/nerf_test.py
sunds-0.4.1.dist-info/LICENSE
sunds-0.4.1.dist-info/WHEEL
sunds-0.4.1.dist-info/METADATA
sunds-0.4.1.dist-info/RECORD
