Metadata-Version: 2.1
Name: sunds
Version: 0.4.1
Summary: Datasets for scene understanding and neural rendering.
Keywords: datasets,scene-understanding,neural rendering,nerf
Author-email: Sunds team <sunds@google.com>
Requires-Python: >=3.7
Classifier: Programming Language :: Python :: 3
Classifier: Programming Language :: Python :: 3 :: Only
Classifier: License :: OSI Approved :: Apache Software License
Classifier: Topic :: Software Development :: Libraries :: Python Modules
Requires-Dist: absl-py
Requires-Dist: etils[epath-no-tf,etqdm]
Requires-Dist: numpy>=1.17
Requires-Dist: tensorflow_datasets>=4.4
Requires-Dist: typing_extensions
Requires-Dist: pytest>=3.4 ; extra == "dev"
Requires-Dist: pytest-xdist ; extra == "dev"
Requires-Dist: pillow ; extra == "dev"
Project-URL: homepage, https://github.com/google-research/sunds
Project-URL: repository, https://github.com/google-research/sunds
Provides-Extra: dev
